[
    {
        "pk": 4, 
        "model": "video.video", 
        "fields": {
            "html_description": null, 
            "rating": "4", 
            "videos": [], 
            "people": [], 
            "created_on": "2008-04-14 00:57:17", 
            "nsfw": false, 
            "embed_code": "<object width=\"400\" height=\"300\"><param name=\"movie\" value=\"http:\/\/www.youtube.com\/v\/LExJ6oN4hUo&hl=en&color1=0x3a3a3a&color2=0x999999&border=1\"><\/param><param name=\"wmode\" value=\"transparent\"><\/param><embed src=\"http:\/\/www.youtube.com\/v\/LExJ6oN4hUo&hl=en&color1=0x3a3a3a&color2=0x999999&border=0\" type=\"application\/x-shockwave-flash\" wmode=\"transparent\" width=\"400\" height=\"300\"><\/embed><\/object>", 
            "title": "Andrew Johnston", 
            "source": 1, 
            "enable_comments": true, 
            "description": "", 
            "tags": "", 
            "last_modified": "2008-04-23 00:10:01", 
            "commentary": "", 
            "path": "", 
            "pub_date": "2008-04-14 00:57:17", 
            "slug": "andrew-johnston", 
            "running_time": "", 
            "places": [], 
            "url": "http:\/\/youtube.com\/watch?v=LExJ6oN4hUo", 
            "video_id": "LExJ6oN4hUo", 
            "html_commentary": null
        }
    }, 
    {
        "pk": 5, 
        "model": "video.video", 
        "fields": {
            "html_description": "<p>Notre Dame baseball pitcher Wade Korpi takes a line drive off the head. The radar gun picked it up off the bat at 100mph.\n<\/p>", 
            "rating": "3", 
            "videos": [], 
            "people": [], 
            "created_on": "2008-04-14 01:06:46", 
            "nsfw": false, 
            "embed_code": "<object width=\"400\" height=\"300\"><param name=\"movie\" value=\"http:\/\/www.youtube.com\/v\/yyeLrLrLA48&hl=en&color1=0x3a3a3a&color2=0x999999&border=1\"><\/param><param name=\"wmode\" value=\"transparent\"><\/param><embed src=\"http:\/\/www.youtube.com\/v\/yyeLrLrLA48&hl=en&color1=0x3a3a3a&color2=0x999999&border=0\" type=\"application\/x-shockwave-flash\" wmode=\"transparent\" width=\"400\" height=\"300\"><\/embed><\/object>", 
            "title": "Line drive off the head", 
            "source": 1, 
            "enable_comments": true, 
            "description": "Notre Dame baseball pitcher Wade Korpi takes a line drive off the head. The radar gun picked it up off the bat at 100mph.", 
            "tags": "baseball", 
            "last_modified": "2008-04-23 00:09:56", 
            "commentary": "Ouch!", 
            "path": "", 
            "pub_date": "2008-04-14 01:06:46", 
            "slug": "line-drive-head", 
            "running_time": "0:40", 
            "places": [], 
            "url": "http:\/\/youtube.com\/watch?v=yyeLrLrLA48", 
            "video_id": "yyeLrLrLA48", 
            "html_commentary": "<p>Ouch!\n<\/p>"
        }
    }, 
    {
        "pk": 6, 
        "model": "video.video", 
        "fields": {
            "html_description": "<p>The Poetic Prophet (AKA The SEO Rapper) is back with another marketing rap. This time he describes how web standards and proper design can affect the ranking and conversion of pages on your site.\n<\/p>", 
            "rating": "4", 
            "videos": [], 
            "people": [], 
            "created_on": "2008-04-14 01:13:14", 
            "nsfw": false, 
            "embed_code": "<object width=\"400\" height=\"300\"><param name=\"movie\" value=\"http:\/\/www.youtube.com\/v\/a0qMe7Z3EYg&hl=en&color1=0x3a3a3a&color2=0x999999&border=1\"><\/param><param name=\"wmode\" value=\"transparent\"><\/param><embed src=\"http:\/\/www.youtube.com\/v\/a0qMe7Z3EYg&hl=en&color1=0x3a3a3a&color2=0x999999&border=0\" type=\"application\/x-shockwave-flash\" wmode=\"transparent\" width=\"400\" height=\"300\"><\/embed><\/object>", 
            "title": "Design Coding", 
            "source": 1, 
            "enable_comments": true, 
            "description": "The Poetic Prophet (AKA The SEO Rapper) is back with another marketing rap. This time he describes how web standards and proper design can affect the ranking and conversion of pages on your site.", 
            "tags": "webdesign rap awesome", 
            "last_modified": "2008-04-23 00:09:37", 
            "commentary": "", 
            "path": "", 
            "pub_date": "2008-04-14 01:13:14", 
            "slug": "design-coding", 
            "running_time": "", 
            "places": [], 
            "url": "http:\/\/youtube.com\/watch?v=a0qMe7Z3EYg", 
            "video_id": "a0qMe7Z3EYg", 
            "html_commentary": null
        }
    }, 
    {
        "pk": 7, 
        "model": "video.video", 
        "fields": {
            "html_description": null, 
            "rating": "2", 
            "videos": [], 
            "people": [], 
            "created_on": "2008-04-23 00:12:48", 
            "nsfw": false, 
            "embed_code": "<object type=\"application\/x-shockwave-flash\" width=\"400\" height=\"300\" data=\"http:\/\/www.vimeo.com\/moogaloop.swf?clip_id=928615&amp;server=www.vimeo.com&amp;fullscreen=1&amp;show_title=0&amp;show_byline=0&amp;show_portrait=0&amp;color=1a1819\"><param name=\"quality\" value=\"best\" \/><param name=\"allowfullscreen\" value=\"true\" \/><param name=\"scale\" value=\"showAll\" \/><param name=\"movie\" value=\"http:\/\/www.vimeo.com\/moogaloop.swf?clip_id=928615&amp;server=www.vimeo.com&amp;fullscreen=1&amp;show_title=0&amp;show_byline=0&amp;show_portrait=0&amp;color=1a1819\" \/><\/object>", 
            "title": "Vimeo test video", 
            "source": 2, 
            "enable_comments": true, 
            "description": "", 
            "tags": "awesome video vimeo", 
            "last_modified": "2008-04-23 00:12:48", 
            "commentary": "", 
            "path": "", 
            "pub_date": "2008-04-23 00:12:48", 
            "slug": "vimeo-test-video", 
            "running_time": "", 
            "places": [], 
            "url": "http:\/\/vimeo.com\/928615", 
            "video_id": "928615", 
            "html_commentary": null
        }
    }, 
    {
        "pk": 8, 
        "model": "video.video", 
        "fields": {
            "html_description": null, 
            "rating": "1", 
            "videos": [], 
            "people": [], 
            "created_on": "2008-04-23 00:15:11", 
            "nsfw": false, 
            "embed_code": "<object type=\"application\/x-shockwave-flash\" data=\"http:\/\/www.collegehumor.com\/moogaloop\/moogaloop.swf?clip_id=1812631&fullscreen=1\" width=\"400\" height=\"300\" ><param name=\"allowfullscreen\" value=\"true\" \/><param name=\"movie\" quality=\"best\" value=\"http:\/\/www.collegehumor.com\/moogaloop\/moogaloop.swf?clip_id=1812631&fullscreen=1\" \/><\/object>", 
            "title": "College humor test video", 
            "source": 3, 
            "enable_comments": true, 
            "description": "", 
            "tags": "", 
            "last_modified": "2008-04-23 00:15:11", 
            "commentary": "", 
            "path": "", 
            "pub_date": "2008-04-23 00:15:11", 
            "slug": "college-humor-test-video", 
            "running_time": "", 
            "places": [], 
            "url": "http:\/\/www.collegehumor.com\/video:1812631", 
            "video_id": "1812631", 
            "html_commentary": null
        }
    }
]
